claudecraftsman/__init__.py
claudecraftsman/__main__.py
claudecraftsman/_version.py
claudecraftsman/compatibility.py
claudecraftsman/migration.py
claudecraftsman/cli/__init__.py
claudecraftsman/cli/app.py
claudecraftsman/cli/commands/__init__.py
claudecraftsman/cli/commands/archive.py
claudecraftsman/cli/commands/health.py
claudecraftsman/cli/commands/hook.py
claudecraftsman/cli/commands/init.py
claudecraftsman/cli/commands/migrate.py
claudecraftsman/cli/commands/registry.py
claudecraftsman/cli/commands/state.py
claudecraftsman/cli/commands/test.py
claudecraftsman/cli/commands/validate.py
claudecraftsman/core/archival.py
claudecraftsman/core/completion_detector.py
claudecraftsman/core/config.py
claudecraftsman/core/enforcement.py
claudecraftsman/core/registry.py
claudecraftsman/core/state.py
claudecraftsman/core/state_enhanced.py
claudecraftsman/core/validation.py
claudecraftsman/hooks/__init__.py
claudecraftsman/hooks/config.py
claudecraftsman/hooks/enforcers.py
claudecraftsman/hooks/handlers.py
claudecraftsman/hooks/validators.py
claudecraftsman/templates/hooks.json
claudecraftsman/templates/framework/framework.md
claudecraftsman/templates/framework/agents/backend-architect.md
claudecraftsman/templates/framework/agents/data-architect.md
claudecraftsman/templates/framework/agents/design-architect.md
claudecraftsman/templates/framework/agents/devops-architect.md
claudecraftsman/templates/framework/agents/frontend-developer.md
claudecraftsman/templates/framework/agents/ml-architect.md
claudecraftsman/templates/framework/agents/product-architect.md
claudecraftsman/templates/framework/agents/python-backend.md
claudecraftsman/templates/framework/agents/qa-architect.md
claudecraftsman/templates/framework/agents/security-architect.md
claudecraftsman/templates/framework/agents/system-architect.md
claudecraftsman/templates/framework/agents/workflow-coordinator.md
claudecraftsman/templates/framework/commands/add.md
claudecraftsman/templates/framework/commands/deploy.md
claudecraftsman-1.0.1.post10.dist-info/METADATA
claudecraftsman-1.0.1.post10.dist-info/WHEEL
claudecraftsman-1.0.1.post10.dist-info/entry_points.txt
claudecraftsman-1.0.1.post10.dist-info/licenses/LICENSE
claudecraftsman-1.0.1.post10.dist-info/RECORD
